numetrics/__init__.py
numetrics/data/val_target_preds.parquet
numetrics-0.2.1.dist-info/LICENSE
numetrics-0.2.1.dist-info/METADATA
numetrics-0.2.1.dist-info/WHEEL
numetrics-0.2.1.dist-info/top_level.txt
numetrics-0.2.1.dist-info/RECORD
