Metadata-Version: 2.1
Name: numetrics
Version: 0.2.1
Summary: Package For Numerai users to check their models performance
Home-page: UNKNOWN
Author: Tim Thabt
Author-email: haithamthabt@hotmail.com
License: MIT
Keywords: numetrics,numerai
Platform: UNKNOWN
